pubmed/__init__.py
pubmed/creation.py
pubmed/esearch.py
pubmed/esummarize.py
pubmed/pubmed_search.py
pypubmed_parser/__init__.py
pypubmed_parser/creation.py
pypubmed_parser/esearch.py
pypubmed_parser/esummarize.py
pypubmed_parser/pubmed_search.py
pypubmed_parser-0.0.1.dist-info/METADATA
pypubmed_parser-0.0.1.dist-info/WHEEL
pypubmed_parser-0.0.1.dist-info/top_level.txt
pypubmed_parser-0.0.1.dist-info/RECORD
